gsheet_api_handler/__init__.py
gsheet_api_handler/main.py
gsheet_api_handler-0.1.3.dist-info/METADATA
gsheet_api_handler-0.1.3.dist-info/WHEEL
gsheet_api_handler-0.1.3.dist-info/top_level.txt
gsheet_api_handler-0.1.3.dist-info/RECORD
