Metadata-Version: 2.1
Name: gsheet-api-handler
Version: 0.1.3
Summary: Paquete para la autenticación y lectura de datos desde Google Sheets con manejo de errores integrado pensado para Google Colab.
Author: Fabrizzio Rutigliano
Author-email: fabrizziorutigliano@gmail.com
Requires-Python: >=3.6
Requires-Dist: gspread
Requires-Dist: google-auth
